heros/__init__.py
heros/capabilities.py
heros/event.py
heros/helper.py
heros/heros.py
heros/inspect.py
heros/serdes.py
heros/zenoh.py
heros/datasource/__init__.py
heros/datasource/datasource.py
heros/datasource/observables.py
heros/datasource/types.py
heros-0.8.7.dist-info/METADATA
heros-0.8.7.dist-info/WHEEL
heros-0.8.7.dist-info/licenses/LICENSE
heros-0.8.7.dist-info/licenses/LICENSE.LESSER
heros-0.8.7.dist-info/RECORD
