Metadata-Version: 2.4
Name: heros
Version: 0.8.7
Summary: Make your objects available everywhere
Project-URL: Homepage, https://gitlab.com/atomiq-project/heros
Project-URL: Repository, https://gitlab.com/atomiq-project/heros
Project-URL: Documentation, https://gitlab.com/atomiq-project/heros/wiki
Project-URL: Bug Tracker, https://gitlab.com/atomiq-project/heros/issues
Author-email: Thomas Niederprüm <t.niederpruem@rptu.de>, Suthep Pomjaksilp <s.pomjaksilp@rptu.de>
Maintainer-email: Thomas Niederprüm <t.niederpruem@rptu.de>, Suthep Pomjaksilp <s.pomjaksilp@rptu.de>
License: LGPL-3.0-or-later
License-File: LICENSE
License-File: LICENSE.LESSER
Keywords: pub/sub,remote object,rpc,zenoh
Classifier: Development Status :: 4 - Beta
Classifier: Environment :: Console
Classifier: Intended Audience :: Developers
Classifier: Intended Audience :: Science/Research
Classifier: License :: OSI Approved :: GNU Lesser General Public License v3 or later (LGPLv3+)
Classifier: Programming Language :: Python :: 3
Classifier: Programming Language :: Python :: 3 :: Only
Classifier: Programming Language :: Python :: 3.10
Classifier: Programming Language :: Python :: 3.11
Classifier: Programming Language :: Python :: 3.12
Classifier: Programming Language :: Python :: 3.13
Classifier: Topic :: Communications
Requires-Python: >=3.10
Requires-Dist: cbor2
Requires-Dist: eclipse-zenoh>=1.1.0
Requires-Dist: numpy
Provides-Extra: dev
Requires-Dist: flake8>=6.0; extra == 'dev'
Requires-Dist: hatch; extra == 'dev'
Requires-Dist: pre-commit>=2.15.0; extra == 'dev'
Requires-Dist: pytest-cov>=4.0; extra == 'dev'
Requires-Dist: pytest-mock>=3; extra == 'dev'
Requires-Dist: pytest>=7.1; extra == 'dev'
Requires-Dist: ruff; extra == 'dev'
Provides-Extra: docs
Requires-Dist: furo>=2024; extra == 'docs'
Requires-Dist: hatch; extra == 'docs'
Requires-Dist: sphinx-argparse; extra == 'docs'
Requires-Dist: sphinx-autoapi>=3; extra == 'docs'
Requires-Dist: sphinx-autodoc-typehints>=3; (python_version >= '3.11') and extra == 'docs'
Requires-Dist: sphinx>=8; (python_version >= '3.11') and extra == 'docs'
Requires-Dist: toml; extra == 'docs'
